xsarsea/__init__.py
xsarsea/config.yml
xsarsea/detrend.py
xsarsea/gradients.py
xsarsea/utils.py
xsarsea/windspeed/__init__.py
xsarsea/windspeed/cmod7.py
xsarsea/windspeed/gmfs.py
xsarsea/windspeed/gmfs_impl.py
xsarsea/windspeed/models.py
xsarsea/windspeed/pickle_luts.py
xsarsea/windspeed/utils.py
xsarsea/windspeed/windspeed.py
xsarsea-2.1.dist-info/licenses/LICENSE
xsarsea-2.1.dist-info/METADATA
xsarsea-2.1.dist-info/WHEEL
xsarsea-2.1.dist-info/top_level.txt
xsarsea-2.1.dist-info/RECORD
